Pytorch1XZiranyuyanChuliShiyongZhinanChuyiFix1/README.md
Pytorch1XZiranyuyanChuliShiyongZhinanChuyiFix1/__init__.py
Pytorch1XZiranyuyanChuliShiyongZhinanChuyiFix1/__main__.py
Pytorch1XZiranyuyanChuliShiyongZhinanChuyiFix1/file.epub
Pytorch1XZiranyuyanChuliShiyongZhinanChuyiFix1/index.html
Pytorch1XZiranyuyanChuliShiyongZhinanChuyiFix1/css/__init__.py
Pytorch1XZiranyuyanChuliShiyongZhinanChuyiFix1/css/annotations.css
Pytorch1XZiranyuyanChuliShiyongZhinanChuyiFix1/css/main.css
Pytorch1XZiranyuyanChuliShiyongZhinanChuyiFix1/css/normalize.css
Pytorch1XZiranyuyanChuliShiyongZhinanChuyiFix1/css/popup.css
Pytorch1XZiranyuyanChuliShiyongZhinanChuyiFix1/font/__init__.py
Pytorch1XZiranyuyanChuliShiyongZhinanChuyiFix1/font/fontello.eot
Pytorch1XZiranyuyanChuliShiyongZhinanChuyiFix1/font/fontello.svg
Pytorch1XZiranyuyanChuliShiyongZhinanChuyiFix1/font/fontello.ttf
Pytorch1XZiranyuyanChuliShiyongZhinanChuyiFix1/font/fontello.woff
Pytorch1XZiranyuyanChuliShiyongZhinanChuyiFix1/img/__init__.py
Pytorch1XZiranyuyanChuliShiyongZhinanChuyiFix1/img/annotator-glyph-sprite.png
Pytorch1XZiranyuyanChuliShiyongZhinanChuyiFix1/img/annotator-icon-sprite.png
Pytorch1XZiranyuyanChuliShiyongZhinanChuyiFix1/img/apple-touch-icon.png
Pytorch1XZiranyuyanChuliShiyongZhinanChuyiFix1/img/cancelfullscreen.png
Pytorch1XZiranyuyanChuliShiyongZhinanChuyiFix1/img/close.png
Pytorch1XZiranyuyanChuliShiyongZhinanChuyiFix1/img/fullscreen.png
Pytorch1XZiranyuyanChuliShiyongZhinanChuyiFix1/img/loader.gif
Pytorch1XZiranyuyanChuliShiyongZhinanChuyiFix1/img/menu-icon.png
Pytorch1XZiranyuyanChuliShiyongZhinanChuyiFix1/img/save.png
Pytorch1XZiranyuyanChuliShiyongZhinanChuyiFix1/img/saved.png
Pytorch1XZiranyuyanChuliShiyongZhinanChuyiFix1/img/settings-s.png
Pytorch1XZiranyuyanChuliShiyongZhinanChuyiFix1/img/settings.png
Pytorch1XZiranyuyanChuliShiyongZhinanChuyiFix1/img/star.png
Pytorch1XZiranyuyanChuliShiyongZhinanChuyiFix1/js/__init__.py
Pytorch1XZiranyuyanChuliShiyongZhinanChuyiFix1/js/epub.js
pytorch_1_x_ziranyuyan_chuli_shiyong_zhinan_chuyi_fix1-2025.3.25.0.dist-info/METADATA
pytorch_1_x_ziranyuyan_chuli_shiyong_zhinan_chuyi_fix1-2025.3.25.0.dist-info/WHEEL
pytorch_1_x_ziranyuyan_chuli_shiyong_zhinan_chuyi_fix1-2025.3.25.0.dist-info/entry_points.txt
pytorch_1_x_ziranyuyan_chuli_shiyong_zhinan_chuyi_fix1-2025.3.25.0.dist-info/top_level.txt
pytorch_1_x_ziranyuyan_chuli_shiyong_zhinan_chuyi_fix1-2025.3.25.0.dist-info/RECORD
